setup.py
batterycharge/batterycharge.py
batterycharge.egg-info/PKG-INFO
batterycharge.egg-info/SOURCES.txt
batterycharge.egg-info/dependency_links.txt
batterycharge.egg-info/entry_points.txt
batterycharge.egg-info/top_level.txt